google_books_highlights_export/__init__.py
google_books_highlights_export/googledrive.py
google_books_highlights_export/notes.py
google_books_highlights_export/vimwiki.py
google_books_highlights_export-0.2.0.dist-info/entry_points.txt
google_books_highlights_export-0.2.0.dist-info/WHEEL
google_books_highlights_export-0.2.0.dist-info/METADATA
google_books_highlights_export-0.2.0.dist-info/RECORD
